[{"page":"survey","name":"Connecticut","label":"Adults satisfied with their area","value":"82%"},{"page":"survey","name":"Black adults","label":"Discriminated against by police","value":"24%"},{"page":"survey","name":"Adults ages 18–34","label":"Bothered by depression","value":"16%"},{"page":"risks","name":"New London","label":"Adults missed medical care in past year","value":"20%"},{"page":"risks","name":"New Britain","label":"Food insecure adults","value":"25%"},{"page":"scores","name":"Connecticut","label":"Community Index score","value":"657"},{"page":"chime","name":"Urban core","label":"Diabetes hospital encounters per 10k residents","value":"1,405"},{"page":"internet","name":"Hartford","label":"Households with no computer","value":"41%"},{"page":"internet","name":"New Haven","label":"Children w/o broadband access","value":"9%"}]
